decaylanguage/__init__.py
decaylanguage/__main__.py
decaylanguage/_version.py
decaylanguage/_version.pyi
decaylanguage/py.typed
decaylanguage/_compat/__init__.py
decaylanguage/_compat/typing.py
decaylanguage/data/DECAY_BELLE2.DEC
decaylanguage/data/DECAY_LHCB.DEC
decaylanguage/data/MintDalitzSpecialParticles.csv
decaylanguage/data/MintDalitzSpecialParticles.fwf
decaylanguage/data/MintDalitzSpecialParticlesLatex.csv
decaylanguage/data/README.rst
decaylanguage/data/__init__.py
decaylanguage/data/ampgen.lark
decaylanguage/data/decfile.lark
decaylanguage/data/particle.lark
decaylanguage/dec/__init__.py
decaylanguage/dec/dec.py
decaylanguage/dec/enums.py
decaylanguage/dec/py.typed
decaylanguage/decay/__init__.py
decaylanguage/decay/decay.py
decaylanguage/decay/py.typed
decaylanguage/decay/viewer.py
decaylanguage/modeling/AmpGenReader.ipynb
decaylanguage/modeling/__init__.py
decaylanguage/modeling/ampgen2goofit.py
decaylanguage/modeling/ampgentransform.py
decaylanguage/modeling/amplitudechain.py
decaylanguage/modeling/decay.py
decaylanguage/modeling/goofit.py
decaylanguage/modeling/py.typed
decaylanguage/utils/__init__.py
decaylanguage/utils/errors.py
decaylanguage/utils/particleutils.py
decaylanguage/utils/utilities.py
decaylanguage-0.20.0.dist-info/METADATA
decaylanguage-0.20.0.dist-info/WHEEL
decaylanguage-0.20.0.dist-info/licenses/AUTHORS.rst
decaylanguage-0.20.0.dist-info/licenses/LICENSE
decaylanguage-0.20.0.dist-info/RECORD
