Metadata-Version: 2.4
Name: decaylanguage
Version: 0.20.0
Summary: A language to describe, manipulate and convert particle decays
Project-URL: Homepage, https://github.com/scikit-hep/decaylanguage
Author-email: Eduardo Rodrigues <eduardo.rodrigues@cern.ch>, Henry Schreiner <henryfs@princeton.edu>
Maintainer-email: Scikit-HEP <scikit-hep-admins@googlegroups.com>
License-File: AUTHORS.rst
License-File: LICENSE
Keywords: HEP,chain,decay,particle,representation
Classifier: Development Status :: 4 - Beta
Classifier: Intended Audience :: Developers
Classifier: Intended Audience :: Science/Research
Classifier: License :: OSI Approved :: BSD License
Classifier: Operating System :: OS Independent
Classifier: Programming Language :: Python
Classifier: Programming Language :: Python :: 3
Classifier: Programming Language :: Python :: 3 :: Only
Classifier: Programming Language :: Python :: 3.9
Classifier: Programming Language :: Python :: 3.10
Classifier: Programming Language :: Python :: 3.11
Classifier: Programming Language :: Python :: 3.12
Classifier: Programming Language :: Python :: 3.13
Classifier: Topic :: Scientific/Engineering
Requires-Python: >=3.9
Requires-Dist: attrs>=19.2
Requires-Dist: graphviz>=0.12.0
Requires-Dist: hepunits>=2.3.5
Requires-Dist: lark>=1.0.0
Requires-Dist: numpy>=1.12
Requires-Dist: pandas>=0.22
Requires-Dist: particle>=0.25.4
Requires-Dist: plumbum>=1.7.0
Provides-Extra: dev
Requires-Dist: pytest>=6; extra == 'dev'
Provides-Extra: docs
Requires-Dist: sphinx-rtd-theme>=0.5.0; extra == 'docs'
Requires-Dist: sphinx>=4; extra == 'docs'
Provides-Extra: test
Requires-Dist: pytest-cov; extra == 'test'
Requires-Dist: pytest>=6; extra == 'test'
